{"paths":{"0":["sounds/Knock",4],"1":["textrues/xiandao_1",0],"2":["textrues/lansekuang",0],"3":["textrues/jiacheng4",0],"4":["textrues/yz",0],"5":["textrues/pic_dimian",0],"6":["textrues/pic_plant11",0],"7":["textrues/8",0],"8":["textrues/jiacheng1",0],"9":["textrues/jiacheng5",0],"10":["textrues/fengexian",0],"11":["textrues/CWpic_plant1",0],"12":["textrues/xuetiao2",0],"13":["textrues/pic_fangzi",0],"14":["font/jian",0],"15":["sounds/hit_2",4],"16":["textrues/pic_liangbian",0],"17":["textrues/pic_plant10",0],"18":["sounds/bonus",4],"19":["textrues/jiacheng3",0],"20":["textrues/pic_plant8",0],"21":["textrues/pic_guanzi",0],"22":["spine/罐子破碎/guanzisuipian",0],"23":["sounds/choose",4],"24":["textrues/hongsekuang",0],"25":["textrues/pic_men",0],"26":["textrues/jiacheng6",0],"27":["textrues/pic_zhongjian",0],"28":["textrues/xuetiao",0],"29":["textrues/zidan11",0],"30":["sounds/launch",4],"31":["spine/罐子破碎/guanzisuipian",6],"32":["font/hpnum",0],"33":["textrues/zhuahen",0],"34":["sounds/hit",4],"35":["textrues/icon_shezhi",0],"36":["textrues/zudang",0],"37":["textrues/wupinfaguang",0],"38":["textrues/CWzidan8",0],"39":["textrues/CWzidan11",0],"40":["textrues/1",0],"41":["textrues/zidan8",0],"42":["textrues/11",0],"44":["textrues/zhuahen",2,1],"45":["textrues/zidan11",2,1],"52":["textrues/pic_plant11",2,1],"54":["textrues/CWzidan11",2,1],"56":["textrues/hongsekuang",2,1],"57":["textrues/xiandao_1",2,1],"58":["textrues/jiacheng3",2,1],"60":["textrues/pic_men",2,1],"61":["textrues/pic_liangbian",2,1],"63":["textrues/pic_dimian",2,1],"65":["prefabs/popups/GTLosePopup",3],"66":["textrues/zudang",2,1],"67":["textrues/pic_guanzi",2,1],"68":["textrues/jiacheng5",2,1],"69":["textrues/zidan8",2,1],"70":["textrues/CWpic_plant1",2,1],"71":["textrues/icon_shezhi",2,1],"75":["textrues/pic_plant8",2,1],"80":["font/jian",2,1],"82":["prefabs/HpProgress",3],"84":["textrues/xuetiao2",2,1],"85":["textrues/pic_zhongjian",2,1],"86":["textrues/8",2,1],"87":["textrues/jiacheng4",2,1],"89":["spine/罐子破碎/guanzisuipian",5],"90":["textrues/fengexian",2,1],"91":["textrues/11",2,1],"93":["textrues/CWzidan8",2,1],"96":["textrues/pic_plant10",2,1],"97":["textrues/pic_fangzi",2,1],"98":["font/hpnum",1],"100":["spine/罐子破碎/guanzisuipian",2,1],"102":["font/hpnum",2,1],"103":["textrues/wupinfaguang",2,1],"105":["textrues/jiacheng6",2,1],"106":["textrues/xuetiao",2,1],"107":["textrues/yz",2,1],"108":["textrues/lansekuang",2,1],"109":["textrues/1",2,1],"111":["prefabs/EquiEffect",3],"114":["textrues/jiacheng1",2,1]},"types":["cc.Texture2D","cc.BitmapFont","cc.SpriteFrame","cc.Prefab","cc.AudioClip","sp.SkeletonData","cc.Asset"],"uuids":["01cV5/inNCy7y3H85Qst4V","04CbID5w1LFY1Pgd1E70+q","0cR4C8e35NlqMujyalBOy0","0flq67ceFBJ56CWAkzIkhE","10IAQrOM5IP4O6fwq7rD8o","15ert21glNZr/KwlBAq39x","21wm7Q4AlLBbIfZ4FlF/Zn","339GtZqsdLoKnrOi4WNADu","35lAQ2PtpIqKmkpnMJzx/j","3couHvvORPXKGWjuqCp63D","4ai94d5a1FVIXCbrxe6jF2","4cz9Ux5OJAEqtcJo/BPLJ0","4d4OnX+I5BCZOgBu6/8sDT","5bpywQBKpCeK0WZg8efu8h","5ecqBzPi9LNpMto4vY7A84","62Hxj9GmRCsYE3nt2EVVzI","64rkLEs3ZBWZRdx+4LRZ9R","6cI/j+YHpF6JHZ/Y8WVyWt","71R0wemOJHNIHqowfkvksw","71h+3jRLVO+6q/VqsP2cgX","730V8GAMtA0pmfDx/1r7qM","73/6Boi6xHGYaX2+hJO2w/","77D9zAL4JJ1LVmoGd88iq4","7cylnYxqtEnbXf0SSm9/8J","85PH0hZ/tFTI1W6+oUG8xS","910j1K1PxGVqSLLhuWwvMR","96TMNC13tLpoOSjlOAJpCl","97IbIlOq5Mj6cJhGcYpJue","aayhKU4nxO24x/QmcCz8cw","b2ULRg+/1LjZb5pQdtCQjo","b4yBTX7ZREbYpaoLnqwPro","c2QqtJHbxN5Km3xOCHUxGv","d1HVdzZyNCDoLam8fHY4he","d8NskFfsRPWoUw/VbteIQt","daPXpH45FPmZt1ohx1Vnki","db/9ffg65BZYFy2VZptYQH","ddBJKK4lNC1IHavyngcxmj","ddyTIflf5Cyp/4XUtlb5s4","deNp66nV9HY7hxHPAHIQ2t","e3hXnot0VOdr9ZbHQWe7m5","f26ASlcFpOuavglvhmKACq","f8lIpT4BtHRqcWxuCPQBjQ","fcwYem339KeY/wXV0euZE/","02sM3lSTpIGoIWsc8LMSDK","17/3gMmf5ECpWcoufcxuit","18PJENKltNuoeyaYv+MlIe","1dxLjP3VBN5pWbyE3Q3xYW","24JpOwBb5NSbccBAZgErTo","24nAp9uDBGeryMK4f4Kk+y","26FpJibgpG34k9uxORowfq","2aFky7cORMaL1qL5kJDY5q","34F7JkvuFHq54vsXNje7nf","37fVTIrptAQ63D5l5wT3Wg","3fmlSCRKdPrIAU5qjtRK4n","3f3dXLSMdNypejV6cvEU1B","40xibLRM9AsogWIWzrzolr","42okkT9EJFeoJ8xWEf3qT2","51AF/DtPBAPrKUWAZg8ZSO","51coT9mvxOYZQ4AqcR/hQC","56DHOAsJ5Hl7/MdYxwwus4","56eAdkgf1GuasCMxXCtPsN","5fRg9bVQFNZqAkBLMINTZX","60A6K9swVP5Z8s70MUcgai","640UgdDMRG64g1GlP3nIi3","66A744N6FHHpLqkCO4ViM+","6bsDlSg2hHEIyeDjolaMeq","6fSf3MGQRKBqjuoR+xb8cc","6flWBolwVC0YECV6LCafs+","73XnwYyw5BhodV5WKDGnuf","75TfCopydGpoy20iAU4RDg","76zdDg8N1Ig4TTLW4Ajz0S","77ycXywV5K8Zg0kk+04WKL","85a12ZXnRNI4j/EvAwAIRg","85vC/8bBxN7bSStotkyzAn","8aGzcht/RNRbQo3TNGgAY2","8bH66DrQFHsoBxVt8un2yI","94qpPRiutMMqTWFzkz3XOn","97AsWTXbpAspKGD0oAe31Y","991BSjsXlMFbXTlePVJ+Wn","9b74MRTd9LWLtIUMDPhjzq","a0zPNRhQ9BBYU43prBEHoL","a1/Bod4K9Mv4RHW9/0xOs5","a6GXEosrpHyKqKyJMiNOBv","a8hR/Jl0ZGj4ZBwPUb5rj9","aab79yXi1JLJnNk4JcL14g","aagR09DypN/JCaPLzxlKgE","aeFVt26tZAM7M3vlpaHzDb","aegZy0hRJDzpv4JNYIyor9","b0hHcJKy1Map34c3LTtP6w","bbZpSHNXNK5o0F/ckbAN+F","bd+jKcQq1DjakJ5bBKcjoL","c4rt0eDHZCSr7T36KbG1el","c4vF/SAZxFFI7o2AG9SVv0","c6HTQ0jTFBgrxjCdeiIC3L","cewgvl/v5NPbN9ZiWECe85","d3OhggiPxO2LHpgO74N/Yp","d49yYQta1H36hg2A+4kURN","d6GtsPnVBKX5Heimdc/1+l","d8ORAnAqxG667y4SNeZsqE","d9VfQYy0RCQLrpUC7+aidf","daRzaJDFRHAKilTOxXk4pn","ddTRK88cxAuanhTm+1TM3+","e3ko4gwRBEiIWtpDaEHCXa","e4jlL8mUhEO6i/mdOmAv07","e5b5EO1I5I4Y32YIof4+KF","e6LzebpFVOBKnpP4pfGyNe","e8s8ZTKtpBOJ76TCt4EhcB","edNViVkINA+otUFg8q51lh","f0K+GZ2J1AHIcz0VZS/HoM","f6TMB7sxNAwaS1kRlm4FpT","fahmml+s5NI44kVOVvk5sC","fczFmanMdOq4lGkTDT+mPI","feCTl0+sxNWKvoUJhO3ZEl","fea+fKmGRJlb3bXdweZWJ+","ffx1UsD4RHkK89pLKap03+","0fn6Q2AytJvZMsIQgVvtG1","29+tg7sSlJh5/C+iB/yY1h","2eFnlUEEJHMIo04nYC3S0s","4atKlpUGtP7LI4JXsXUYYV","542nJvF1hLh4QHvVGy2TAT","5cPDvTvVxPl66ErjAWa4BA","5dPn2/DLZLgL5Hogl+ZcMK","5d1wMzcmVOJpYGOWmshbh5","6fGf5nr0RC96ZZkrQ3sTc4","72FGEEQlFOBovNUSK9IZ+L","769cpa7KJKn7ehKESj/zpi","7a/QZLET9IDreTiBfRn2PD","7eBAgLiuhAPLbMJblmqxVN","81iRrZZX9ImoLE/CLyW1aA","81+6z+gH9MGLdUNSTZb6xY","86bZ4PwAJGSZn4/AHdz08p","8eucXoWuZC05pK+ruRyV4Y","988RV/+MxJRpKjdOMfNMxd","bbAv7qjW5IN51Eodcnaf+W","c96a5C9O5JF5cZFJ1DYwEI","d2TtVu4kNJDozPe08ajrfG","d89zKcqIRDY6k/L1Fbgt0X","dbpabiINFGaJqECyKbMsgR","dc8DhhYNdDmZ++/VpLESUQ","ddQ1Lz1p9BXKfnOZQBR01x","ecSzh6CRBBXpZbfs8NFC0n","ecpdLyjvZBwrvm+cedCcQy","ec/oMqtY5BgZmpTEYdSC/T","eeqJzpp4tKvYxHFXbXecG+","f8i0BhOZ9Ly6xVLbYd/4Kb","f9dLILvLdC2YxoGw6668ch"],"scenes":{"db://assets/res_GuardingTheBridge/GuardingTheBridge.fire":101},"redirect":[126,0,141,0],"deps":["internal"],"packs":{"0c384d448":[43,1,2,3,4,5,46,6,47,48,49,50,7,51,8,9,53,55,10,11,12,13,14,62,16,64,17,19,20,21,22,24,72,73,74,25,76,26,77,27,78,79,81,83,28,88,29,92,94,32,95,33,99,35,36,37,38,39,104,40,41,110,42,112,113],"0c8ba6fc3":[98,102],"0d308c9e8":[44,56,118,57,60,120,121,122,61,63,123,66,67,124,70,125,71,127,128,130,132,80,85,86,133,90,91,135,96,97,137,138,139,101,103,142,107,143,108,109,144,145],"0f74d9551":[115,116,117,119,65,129,131,134,136,140],"0ff0051bc":[82,84,106]},"name":"res_GuardingTheBridge","importBase":"import","nativeBase":"native","debug":false,"isZip":false,"encrypted":false,"versions":{"import":[0,"57ff6","0c384d448","4524a","0c8ba6fc3","20820","0d308c9e8","dfe8d","0f74d9551","a12a2","0ff0051bc","41f5f",45,"c7fa2",52,"0e3c7",54,"375a2",58,"6d0d9",59,"f1b86",15,"05bf5",18,"cd9e2",68,"f3970",69,"66a7d",23,"51f74",75,"eb71a",87,"fab7f",30,"87c95",89,"fc77d",31,"c1020",93,"6f3f5",34,"ba30d",100,"283c2",105,"b9994",111,"cde20",114,"8dd86"],"native":[0,"06c42",43,"e9365",1,"e850d",2,"181d7",3,"5659f",4,"acc7d",5,"3ac5f",46,"08da5",6,"78b51",47,"96053",48,"e10f6",49,"96f22",50,"19557",7,"3030b",51,"a5770",8,"a7f0c",9,"06c96",53,"e1f99",55,"4dacc",10,"48827",11,"2acd0",12,"576e2",59,"f12b2",13,"64d9a",14,"c51d4",62,"3f5e7",15,"0e90d",16,"66794",64,"e433b",17,"5bbb5",18,"5ec9c",19,"7c85f",20,"4753a",21,"3398a",22,"2dca8",23,"7defc",24,"f854e",72,"d9410",73,"b8eee",74,"88431",25,"af740",76,"687d4",26,"a0c73",77,"bbcc8",27,"a3db1",78,"149d9",79,"6c67b",81,"0a539",83,"f6d2a",28,"336fb",88,"679ae",29,"dc1a5",30,"24f13",31,"4b172",92,"e527b",94,"42c54",32,"6c64b",95,"1baa4",33,"0c9a3",99,"ff71f",34,"9a0e9",35,"dac0a",36,"0880b",37,"218a2",38,"7ce85",39,"65314",104,"c4824",40,"a3ddd",41,"1c24f",110,"c0bf4",42,"8b45e",112,"4da25",113,"f3003"]}}