{"paths":{"0":["unkown/pic_loading_xiao",2],"1":["unkown/pic_loadingtiao_di",2],"2":["unkown/b43ff3c2-02bb-4874-81f7-f2dea6970f18",2],"3":["unkown/e851e89b-faa2-4484-bea6-5c01dd9f06e2",2],"4":["unkown/71561142-4c83-4933-afca-cb7a17f67053",2],"5":["unkown/pic_jiangshitou",2],"6":["unkown/pic_loadingtiao",2],"7":["unkown/公司LOGO",2],"8":["unkown/b43ff3c2-02bb-4874-81f7-f2dea6970f18",1,1],"9":["unkown/e851e89b-faa2-4484-bea6-5c01dd9f06e2",1,1],"10":["uis/LoadUI",0],"11":["unkown/71561142-4c83-4933-afca-cb7a17f67053",1,1],"12":["unkown/pic_loading_xiao",1,1],"13":["unkown/pic_jiangshitou",1,1],"14":["unkown/公司LOGO",1,1],"16":["unkown/pic_loadingtiao_di",1,1],"17":["unkown/pic_loadingtiao",1,1]},"types":["cc.Prefab","cc.SpriteFrame","cc.Texture2D"],"uuids":["01ABkqyWVGX4oiB3ritefV","0aenbJpqhCn72BFDW5EB1s","73GiA7/ApIG5T1xis6h34y","7a9l1e4xNEwZEYyYHWoL0T","acyvGbHrJCF6lDJF6pe3rP","bcVm6hNsxPsLqrYW8F50IC","d1C7wjBcBOtbBlkQLQYoUL","ece/hZpiZBTY7ZGPnE9gB4","00aRaGq0NLua9+4wFmJw0B","14ITViojpPKYvCabE2Zxoz","1bK9BOcB9EVqL+PwpAhMxz","29OlCaD2RFFqHxh8xrUW1H","385MOws9pEmYRERij2c2zr","5eoW8Ia8lNpo1bz015A5BF","6abmJiRz5FhpRNXuG9sksr","71VhFCTINJM6/Ky3oX9nBT","9fUeFZ2DhATahLOAQdAcW3","edBze40aVLEK12jJreQCb2","29FYIk+N1GYaeWH/q1NxQO","7a/QZLET9IDreTiBfRn2PD","ecpdLyjvZBwrvm+cedCcQy"],"scenes":{},"redirect":[19,0,20,0],"deps":["internal"],"packs":{"09c78a7e6":[0,1,15,2,3,4,5,6,7],"0ad8eb984":[10,18,12,13,14,16,17]},"name":"Load","importBase":"import","nativeBase":"native","debug":false,"isZip":false,"encrypted":false,"versions":{"import":[8,"db5a5","09c78a7e6","e3c82","0ad8eb984","cb9e7",9,"38a04",11,"b5719"],"native":[0,"84439",1,"377df",15,"c06a9",2,"0003d",3,"71323",4,"2c7bc",5,"c6a22",6,"83e0c",7,"4e071"]}}